<?xml version="1.0" encoding="UTF-8"?>
<!DOCTYPE mapper PUBLIC "-//mybatis.org//DTD Mapper 3.0//EN" "http://mybatis.org/dtd/mybatis-3-mapper.dtd">
<mapper namespace="com.jzfq.rms.product.persistence.dao.ICheckItemsDAO">
  <resultMap id="BaseResultMap" type="com.jzfq.rms.product.bean.CheckItems">
    <!--
      WARNING - @mbg.generated
      This element is automatically generated by MyBatis Generator, do not modify.
      This element was generated on Thu Nov 09 14:47:42 CST 2017.
    -->
    <id column="check_item_id" jdbcType="INTEGER" property="checkItemId" />
    <result column="check_items" jdbcType="INTEGER" property="checkItems" />
    <result column="check_item_value" jdbcType="VARCHAR" property="checkItemValue" />
    <result column="check_item_description" jdbcType="VARCHAR" property="checkItemDescription" />
    <result column="check_item_type" jdbcType="INTEGER" property="checkItemType" />
    <result column="check_item_type_name" jdbcType="VARCHAR" property="checkItemTypeName" />
    <result column="creator" jdbcType="VARCHAR" property="creator" />
    <result column="create_time" jdbcType="TIMESTAMP" property="createTime" />
    <result column="updater" jdbcType="VARCHAR" property="updater" />
    <result column="update_time" jdbcType="TIMESTAMP" property="updateTime" />
    <result column="deleteflag" jdbcType="INTEGER" property="deleteflag" />
  </resultMap>
  <sql id="Example_Where_Clause">
    <!--
      WARNING - @mbg.generated
      This element is automatically generated by MyBatis Generator, do not modify.
      This element was generated on Thu Nov 09 14:47:42 CST 2017.
    -->
    <where>
      <foreach collection="oredCriteria" item="criteria" separator="or">
        <if test="criteria.valid">
          <trim prefix="(" prefixOverrides="and" suffix=")">
            <foreach collection="criteria.criteria" item="criterion">
              <choose>
                <when test="criterion.noValue">
                  and ${criterion.condition}
                </when>
                <when test="criterion.singleValue">
                  and ${criterion.condition} #{criterion.value}
                </when>
                <when test="criterion.betweenValue">
                  and ${criterion.condition} #{criterion.value} and #{criterion.secondValue}
                </when>
                <when test="criterion.listValue">
                  and ${criterion.condition}
                  <foreach close=")" collection="criterion.value" item="listItem" open="(" separator=",">
                    #{listItem}
                  </foreach>
                </when>
              </choose>
            </foreach>
          </trim>
        </if>
      </foreach>
    </where>
  </sql>
  <sql id="Update_By_Example_Where_Clause">
    <!--
      WARNING - @mbg.generated
      This element is automatically generated by MyBatis Generator, do not modify.
      This element was generated on Thu Nov 09 14:47:42 CST 2017.
    -->
    <where>
      <foreach collection="example.oredCriteria" item="criteria" separator="or">
        <if test="criteria.valid">
          <trim prefix="(" prefixOverrides="and" suffix=")">
            <foreach collection="criteria.criteria" item="criterion">
              <choose>
                <when test="criterion.noValue">
                  and ${criterion.condition}
                </when>
                <when test="criterion.singleValue">
                  and ${criterion.condition} #{criterion.value}
                </when>
                <when test="criterion.betweenValue">
                  and ${criterion.condition} #{criterion.value} and #{criterion.secondValue}
                </when>
                <when test="criterion.listValue">
                  and ${criterion.condition}
                  <foreach close=")" collection="criterion.value" item="listItem" open="(" separator=",">
                    #{listItem}
                  </foreach>
                </when>
              </choose>
            </foreach>
          </trim>
        </if>
      </foreach>
    </where>
  </sql>
  <sql id="Base_Column_List">
    <!--
      WARNING - @mbg.generated
      This element is automatically generated by MyBatis Generator, do not modify.
      This element was generated on Thu Nov 09 14:47:42 CST 2017.
    -->
    `check_item_id`, `check_items`, `check_item_value`, `check_item_description`, `check_item_type`, 
    `check_item_type_name`, `creator`, `create_time`, `updater`, `update_time`, `deleteflag`
  </sql>
  <select id="selectByExample" parameterType="com.jzfq.rms.product.bean.CheckItemsExample" resultMap="BaseResultMap">
    <!--
      WARNING - @mbg.generated
      This element is automatically generated by MyBatis Generator, do not modify.
      This element was generated on Thu Nov 09 14:47:42 CST 2017.
    -->
    select
    <if test="distinct">
      distinct
    </if>
    <include refid="Base_Column_List" />
    from `check_items`
    <if test="_parameter != null">
      <include refid="Example_Where_Clause" />
    </if>
    <if test="orderByClause != null">
      order by ${orderByClause}
    </if>
  </select>
  <select id="selectByPrimaryKey" parameterType="java.lang.Integer" resultMap="BaseResultMap">
    <!--
      WARNING - @mbg.generated
      This element is automatically generated by MyBatis Generator, do not modify.
      This element was generated on Thu Nov 09 14:47:42 CST 2017.
    -->
    select 
    <include refid="Base_Column_List" />
    from `check_items`
    where `check_item_id` = #{checkItemId,jdbcType=INTEGER}
  </select>
  <delete id="deleteByPrimaryKey" parameterType="java.lang.Integer">
    <!--
      WARNING - @mbg.generated
      This element is automatically generated by MyBatis Generator, do not modify.
      This element was generated on Thu Nov 09 14:47:42 CST 2017.
    -->
    delete from `check_items`
    where `check_item_id` = #{checkItemId,jdbcType=INTEGER}
  </delete>
  <insert id="insert" parameterType="com.jzfq.rms.product.bean.CheckItems">
    <!--
      WARNING - @mbg.generated
      This element is automatically generated by MyBatis Generator, do not modify.
      This element was generated on Thu Nov 09 14:47:42 CST 2017.
    -->
    insert into `check_items` (`check_item_id`, `check_items`, `check_item_value`, 
      `check_item_description`, `check_item_type`, `check_item_type_name`, 
      `creator`, `create_time`, `updater`, 
      `update_time`, `deleteflag`)
    values (#{checkItemId,jdbcType=INTEGER}, #{checkItems,jdbcType=INTEGER}, #{checkItemValue,jdbcType=VARCHAR}, 
      #{checkItemDescription,jdbcType=VARCHAR}, #{checkItemType,jdbcType=INTEGER}, #{checkItemTypeName,jdbcType=VARCHAR}, 
      #{creator,jdbcType=VARCHAR}, #{createTime,jdbcType=TIMESTAMP}, #{updater,jdbcType=VARCHAR}, 
      #{updateTime,jdbcType=TIMESTAMP}, #{deleteflag,jdbcType=INTEGER})
  </insert>
  <insert id="insertSelective" parameterType="com.jzfq.rms.product.bean.CheckItems">
    <!--
      WARNING - @mbg.generated
      This element is automatically generated by MyBatis Generator, do not modify.
      This element was generated on Thu Nov 09 14:47:42 CST 2017.
    -->
    insert into `check_items`
    <trim prefix="(" suffix=")" suffixOverrides=",">
      <if test="checkItemId != null">
        `check_item_id`,
      </if>
      <if test="checkItems != null">
        `check_items`,
      </if>
      <if test="checkItemValue != null">
        `check_item_value`,
      </if>
      <if test="checkItemDescription != null">
        `check_item_description`,
      </if>
      <if test="checkItemType != null">
        `check_item_type`,
      </if>
      <if test="checkItemTypeName != null">
        `check_item_type_name`,
      </if>
      <if test="creator != null">
        `creator`,
      </if>
      <if test="createTime != null">
        `create_time`,
      </if>
      <if test="updater != null">
        `updater`,
      </if>
      <if test="updateTime != null">
        `update_time`,
      </if>
      <if test="deleteflag != null">
        `deleteflag`,
      </if>
    </trim>
    <trim prefix="values (" suffix=")" suffixOverrides=",">
      <if test="checkItemId != null">
        #{checkItemId,jdbcType=INTEGER},
      </if>
      <if test="checkItems != null">
        #{checkItems,jdbcType=INTEGER},
      </if>
      <if test="checkItemValue != null">
        #{checkItemValue,jdbcType=VARCHAR},
      </if>
      <if test="checkItemDescription != null">
        #{checkItemDescription,jdbcType=VARCHAR},
      </if>
      <if test="checkItemType != null">
        #{checkItemType,jdbcType=INTEGER},
      </if>
      <if test="checkItemTypeName != null">
        #{checkItemTypeName,jdbcType=VARCHAR},
      </if>
      <if test="creator != null">
        #{creator,jdbcType=VARCHAR},
      </if>
      <if test="createTime != null">
        #{createTime,jdbcType=TIMESTAMP},
      </if>
      <if test="updater != null">
        #{updater,jdbcType=VARCHAR},
      </if>
      <if test="updateTime != null">
        #{updateTime,jdbcType=TIMESTAMP},
      </if>
      <if test="deleteflag != null">
        #{deleteflag,jdbcType=INTEGER},
      </if>
    </trim>
  </insert>
  <select id="countByExample" parameterType="com.jzfq.rms.product.bean.CheckItemsExample" resultType="java.lang.Long">
    <!--
      WARNING - @mbg.generated
      This element is automatically generated by MyBatis Generator, do not modify.
      This element was generated on Thu Nov 09 14:47:42 CST 2017.
    -->
    select count(*) from `check_items`
    <if test="_parameter != null">
      <include refid="Example_Where_Clause" />
    </if>
  </select>
  <update id="updateByExampleSelective" parameterType="map">
    <!--
      WARNING - @mbg.generated
      This element is automatically generated by MyBatis Generator, do not modify.
      This element was generated on Thu Nov 09 14:47:42 CST 2017.
    -->
    update `check_items`
    <set>
      <if test="record.checkItemId != null">
        `check_item_id` = #{record.checkItemId,jdbcType=INTEGER},
      </if>
      <if test="record.checkItems != null">
        `check_items` = #{record.checkItems,jdbcType=INTEGER},
      </if>
      <if test="record.checkItemValue != null">
        `check_item_value` = #{record.checkItemValue,jdbcType=VARCHAR},
      </if>
      <if test="record.checkItemDescription != null">
        `check_item_description` = #{record.checkItemDescription,jdbcType=VARCHAR},
      </if>
      <if test="record.checkItemType != null">
        `check_item_type` = #{record.checkItemType,jdbcType=INTEGER},
      </if>
      <if test="record.checkItemTypeName != null">
        `check_item_type_name` = #{record.checkItemTypeName,jdbcType=VARCHAR},
      </if>
      <if test="record.creator != null">
        `creator` = #{record.creator,jdbcType=VARCHAR},
      </if>
      <if test="record.createTime != null">
        `create_time` = #{record.createTime,jdbcType=TIMESTAMP},
      </if>
      <if test="record.updater != null">
        `updater` = #{record.updater,jdbcType=VARCHAR},
      </if>
      <if test="record.updateTime != null">
        `update_time` = #{record.updateTime,jdbcType=TIMESTAMP},
      </if>
      <if test="record.deleteflag != null">
        `deleteflag` = #{record.deleteflag,jdbcType=INTEGER},
      </if>
    </set>
    <if test="_parameter != null">
      <include refid="Update_By_Example_Where_Clause" />
    </if>
  </update>
  <update id="updateByExample" parameterType="map">
    <!--
      WARNING - @mbg.generated
      This element is automatically generated by MyBatis Generator, do not modify.
      This element was generated on Thu Nov 09 14:47:42 CST 2017.
    -->
    update `check_items`
    set `check_item_id` = #{record.checkItemId,jdbcType=INTEGER},
      `check_items` = #{record.checkItems,jdbcType=INTEGER},
      `check_item_value` = #{record.checkItemValue,jdbcType=VARCHAR},
      `check_item_description` = #{record.checkItemDescription,jdbcType=VARCHAR},
      `check_item_type` = #{record.checkItemType,jdbcType=INTEGER},
      `check_item_type_name` = #{record.checkItemTypeName,jdbcType=VARCHAR},
      `creator` = #{record.creator,jdbcType=VARCHAR},
      `create_time` = #{record.createTime,jdbcType=TIMESTAMP},
      `updater` = #{record.updater,jdbcType=VARCHAR},
      `update_time` = #{record.updateTime,jdbcType=TIMESTAMP},
      `deleteflag` = #{record.deleteflag,jdbcType=INTEGER}
    <if test="_parameter != null">
      <include refid="Update_By_Example_Where_Clause" />
    </if>
  </update>
  <update id="updateByPrimaryKeySelective" parameterType="com.jzfq.rms.product.bean.CheckItems">
    <!--
      WARNING - @mbg.generated
      This element is automatically generated by MyBatis Generator, do not modify.
      This element was generated on Thu Nov 09 14:47:42 CST 2017.
    -->
    update `check_items`
    <set>
      <if test="checkItems != null">
        `check_items` = #{checkItems,jdbcType=INTEGER},
      </if>
      <if test="checkItemValue != null">
        `check_item_value` = #{checkItemValue,jdbcType=VARCHAR},
      </if>
      <if test="checkItemDescription != null">
        `check_item_description` = #{checkItemDescription,jdbcType=VARCHAR},
      </if>
      <if test="checkItemType != null">
        `check_item_type` = #{checkItemType,jdbcType=INTEGER},
      </if>
      <if test="checkItemTypeName != null">
        `check_item_type_name` = #{checkItemTypeName,jdbcType=VARCHAR},
      </if>
      <if test="creator != null">
        `creator` = #{creator,jdbcType=VARCHAR},
      </if>
      <if test="createTime != null">
        `create_time` = #{createTime,jdbcType=TIMESTAMP},
      </if>
      <if test="updater != null">
        `updater` = #{updater,jdbcType=VARCHAR},
      </if>
      <if test="updateTime != null">
        `update_time` = #{updateTime,jdbcType=TIMESTAMP},
      </if>
      <if test="deleteflag != null">
        `deleteflag` = #{deleteflag,jdbcType=INTEGER},
      </if>
    </set>
    where `check_item_id` = #{checkItemId,jdbcType=INTEGER}
  </update>
  <update id="updateByPrimaryKey" parameterType="com.jzfq.rms.product.bean.CheckItems">
    <!--
      WARNING - @mbg.generated
      This element is automatically generated by MyBatis Generator, do not modify.
      This element was generated on Thu Nov 09 14:47:42 CST 2017.
    -->
    update `check_items`
    set `check_items` = #{checkItems,jdbcType=INTEGER},
      `check_item_value` = #{checkItemValue,jdbcType=VARCHAR},
      `check_item_description` = #{checkItemDescription,jdbcType=VARCHAR},
      `check_item_type` = #{checkItemType,jdbcType=INTEGER},
      `check_item_type_name` = #{checkItemTypeName,jdbcType=VARCHAR},
      `creator` = #{creator,jdbcType=VARCHAR},
      `create_time` = #{createTime,jdbcType=TIMESTAMP},
      `updater` = #{updater,jdbcType=VARCHAR},
      `update_time` = #{updateTime,jdbcType=TIMESTAMP},
      `deleteflag` = #{deleteflag,jdbcType=INTEGER}
    where `check_item_id` = #{checkItemId,jdbcType=INTEGER}
  </update>
</mapper>